README.md
setup.cfg
setup.py
connio/__init__.py
connio.egg-info/PKG-INFO
connio.egg-info/SOURCES.txt
connio.egg-info/dependency_links.txt
connio.egg-info/requires.txt
connio.egg-info/top_level.txt
connio.egg-info/zip-safe