Metadata-Version: 2.1
Name: connio
Version: 0.2.0
Summary: Concurrency agnostic socket API
Home-page: https://tiagocoutinho.github.io/connio/
Author: Jose Tiago Macara Coutinho
Author-email: coutinhotiago@gmail.com
License: GPLv3+
Project-URL: Documentation, https://tiagocoutinho.github.io/connio/
Project-URL: Source, https://github.com/tiagocoutinho/connio/
Keywords: socket,tcp,ser2net,serial,rs232,rfc2217,asyncio
Platform: UNKNOWN
Classifier: Development Status :: 2 - Pre-Alpha
Classifier: Intended Audience :: Developers
Classifier: Natural Language :: English
Classifier: Programming Language :: Python :: 3
Classifier: Programming Language :: Python :: 3.5
Classifier: Programming Language :: Python :: 3.6
Classifier: Programming Language :: Python :: 3.7
Classifier: Programming Language :: Python :: 3.8
Requires-Python: >=3.5
